__init__.py
ab/__init__.py
ab/const.py
ab/core.py
ab/apps/__init__.py
ab/apps/flask.py
ab/apps/gunicorn.py
ab/apps/prometheus.py
ab/client/__init__.py
ab/client/cli.py
ab/client/crypto_cli.py
ab/config/__init__.py
ab/config/config.py
ab/config/default_config.py
ab/controllers/__init__.py
ab/controllers/algorithm.py
ab/controllers/doc.py
ab/controllers/routing.py
ab/decorate/__init__.py
ab/decorate/on_starting_hooks.py
ab/decorate/warmup.py
ab/decorate/when_ready_hooks.py
ab/endpoint/__init__.py
ab/endpoint/registry.py
ab/keys/__init__.py
ab/keys/crypto.py
ab/keys/data.py
ab/plugins/__init__.py
ab/plugins/base_plugin.py
ab/plugins/platform.py
ab/plugins/prob.py
ab/plugins/cache/__init__.py
ab/plugins/cache/redis.py
ab/plugins/calllimit/__init__.py
ab/plugins/calllimit/core.py
ab/plugins/config/__init__.py
ab/plugins/config/config_reader.py
ab/plugins/data/__init__.py
ab/plugins/data/data_reader.py
ab/plugins/data/engine.py
ab/services/__init__.py
ab/services/api_executor.py
ab/task/__init__.py
ab/task/recorder.py
ab/task/task.py
ab/templates/__init__.py
ab/templates/cython_setup.py
ab/tests/__init__.py
ab/tests/pytest_plugin.py
ab/utils/__init__.py
ab/utils/ab_config.py
ab/utils/abt.py
ab/utils/abt_config.py
ab/utils/abt_logger.py
ab/utils/env.py
ab/utils/exceptions.py
ab/utils/fixture.py
ab/utils/logger.py
ab/utils/mixes.py
ab/utils/network.py
ab/utils/os_util.py
ab/utils/oss_util.py
ab/utils/prometheus.py
ab/utils/python_util.py
ab/utils/rate_limit.py
ab/utils/rate_limit_by_second.py
ab/utils/reflection.py
ab/utils/sae_util.py
ab/utils/security.py
ab/utils/serializer.py
python_fast_service-0.2.1.dist-info/LICENSE
python_fast_service-0.2.1.dist-info/METADATA
python_fast_service-0.2.1.dist-info/WHEEL
python_fast_service-0.2.1.dist-info/entry_points.txt
python_fast_service-0.2.1.dist-info/top_level.txt
python_fast_service-0.2.1.dist-info/RECORD
