Metadata-Version: 2.1
Name: python-fast-service
Version: 0.2.1
Summary: This project can quickly package your Python code into a service that is ready for production environments.
Author-email: cactusgame <704300624@qq.com>
License: Apache License
Project-URL: Homepage, https://github.com/cactusgame/python-fast-service
Keywords: python,backend,service
Classifier: License :: OSI Approved :: MIT License
Classifier: Programming Language :: Python
Classifier: Programming Language :: Python :: 3
Requires-Python: >=3.8
License-File: LICENSE
Requires-Dist: pandas>=2.0
Requires-Dist: numpy>=1.23
Requires-Dist: simplejson==3.17.0
Requires-Dist: flask==1.1.4
Requires-Dist: markupsafe==2.0.1
Requires-Dist: gunicorn==20.0.4
Requires-Dist: prometheus-client==0.8.0
Requires-Dist: requests>=2.24.0
Requires-Dist: Jinja2==2.11.2
Requires-Dist: click==7.1.2
Requires-Dist: Cython>=0.29.21
Requires-Dist: pytest==5.4.3
Requires-Dist: redis==6.1.1
Requires-Dist: pyyaml
Requires-Dist: pyAesCrypt
Provides-Extra: dev
Requires-Dist: pip-tools; extra == "dev"
Requires-Dist: pytest; extra == "dev"
